[
  {
    "id": 6,
    "category": "skincare",
    "section": "basic",
    "name": "تنظيف عميق",
    "duration": "60 دقيقة",
    "content": "جلسة تنظيف عميق للبشرة تتضمن إزالة الشوائب والرؤوس السوداء، مما يساعد على تنقية البشرة ومنحها مظهراً صحياً ونظيفاً.",
    "price": 50
  },
  {
    "id": 7,
    "category": "skincare",
    "section": "basic",
    "name": "هيدرافيشل",
    "duration": "45 دقيقة",
    "content": "جلسة متطورة لتنظيف البشرة بعمق باستخدام تقنية الهيدرافيشل، تساعد على إزالة الشوائب وترطيب البشرة بشكل فوري.",
    "price": 60
  },
  {
    "id": 8,
    "category": "skincare",
    "section": "basic",
    "name": "تنظيف مع ماسك كولاجين",
    "duration": "70 دقيقة",
    "content": "جلسة تنظيف عميق يليها تطبيق ماسك الكولاجين الذي يساعد على ترطيب البشرة وشدّها ومنحها إشراقة طبيعية.",
    "price": 65
  },
  {
    "id": 9,
    "category": "skincare",
    "section": "basic",
    "name": "تنظيف بالبخار وإزالة الرؤوس السوداء",
    "duration": "60 دقيقة",
    "content": "جلسة تنظيف بالبخار لفتح المسام وإزالة الرؤوس السوداء بفعالية، مما يمنح البشرة مظهراً نظيفاً ومنتعشاً.",
    "price": 55
  },
  {
    "id": 10,
    "category": "skincare",
    "section": "basic",
    "name": "جلسة ترطيب عميق",
    "duration": "50 دقيقة",
    "content": "جلسة مكثفة لترطيب البشرة الجافة، تساعد على استعادة التوازن الطبيعي ومنح البشرة نعومة ولمعاناً.",
    "price": 60
  },

  {
    "id": 11,
    "category": "skincare",
    "section": "peeling",
    "name": "تقشير كيميائي",
    "duration": "40 دقيقة",
    "content": "تقشير كيميائي يزيل الخلايا الميتة ويجدد البشرة، مما يساعد على تحسين الملمس وتقليل التصبغات.",
    "price": 70
  },
  {
    "id": 12,
    "category": "skincare",
    "section": "peeling",
    "name": "تقشير كربوني",
    "duration": "30 دقيقة",
    "content": "تقنية حديثة باستخدام الكربون لتنظيف المسام بعمق وتقليل الدهون وتحسين مظهر البشرة.",
    "price": 80
  },
  {
    "id": 13,
    "category": "skincare",
    "section": "peeling",
    "name": "تقشير أعشاب طبيعي",
    "duration": "50 دقيقة",
    "content": "تقشير طبيعي بالأعشاب يساعد على تجديد البشرة وتحفيز الكولاجين بطريقة آمنة.",
    "price": 75
  },
  {
    "id": 14,
    "category": "skincare",
    "section": "peeling",
    "name": "تقشير طحالب",
    "duration": "45 دقيقة",
    "content": "جلسة تقشير باستخدام الطحالب الطبيعية لتغذية البشرة وإزالة الخلايا الميتة.",
    "price": 70
  },
  {
    "id": 15,
    "category": "skincare",
    "section": "peeling",
    "name": "تقشير إنزيمي",
    "duration": "35 دقيقة",
    "content": "تقشير لطيف باستخدام إنزيمات طبيعية مناسب للبشرة الحساسة بدون تهيّج.",
    "price": 65
  },

  {
    "id": 16,
    "category": "skincare",
    "section": "treatment",
    "name": "علاج حب الشباب",
    "duration": "50 دقيقة",
    "content": "علاج متخصص للتخلص من حب الشباب وتقليل الالتهابات وتحسين مظهر البشرة.",
    "price": 65
  },
  {
    "id": 17,
    "category": "skincare",
    "section": "treatment",
    "name": "علاج الكلف",
    "duration": "60 دقيقة",
    "content": "جلسة لعلاج الكلف وتوحيد لون البشرة باستخدام تقنيات حديثة.",
    "price": 90
  },
  {
    "id": 18,
    "category": "skincare",
    "section": "treatment",
    "name": "علاج التصبغات",
    "duration": "55 دقيقة",
    "content": "علاج فعال لتفتيح التصبغات والبقع الداكنة واستعادة لون البشرة الطبيعي.",
    "price": 85
  },
  {
    "id": 19,
    "category": "skincare",
    "section": "treatment",
    "name": "علاج المسام الواسعة",
    "duration": "45 دقيقة",
    "content": "تقليل مظهر المسام الواسعة وتنظيفها بعمق للحصول على بشرة ناعمة.",
    "price": 70
  },
  {
    "id": 20,
    "category": "skincare",
    "section": "treatment",
    "name": "علاج البشرة الدهنية",
    "duration": "50 دقيقة",
    "content": "تنظيم إفراز الدهون وتقليل اللمعان للحصول على بشرة متوازنة.",
    "price": 75
  },
  {
    "id": 21,
    "category": "skincare",
    "section": "treatment",
    "name": "علاج البشرة الحساسة",
    "duration": "50 دقيقة",
    "content": "علاج مخصص لتهدئة البشرة الحساسة وتقليل الاحمرار مع ترطيب عميق.",
    "price": 80
  }
]
